Memory/Q2.v
`timescale 1ns/1ps

module rw16x8_sync (
    output reg [7:0] dout,
    input wire [3:0] address,
    input wire WE,RE,
    input wire [7:0] din,
    input clk
);

    // 16x8 memory array (16 locations, each 8 bits wide)
    reg [7:0] RW [0:15];

    always @ (posedge clk) begin
        if (WE) begin
            RW[address] <= din;
        end
        else if (RE) begin
            dout <= RW[address];
        end
        else if (WE && RE) begin
        $display("Invalid condition");
        end
        else begin
        $display("No operation");
        end
    end
endmodule


`timescale 1ns/1ps

module tb_rw16x8_sync;
    reg [3:0] address;
    reg WE, RE;
    reg [7:0] din;
    reg clk;
    wire [7:0] dout;

    rw16x8_sync dut (
        .dout(dout),
        .address(address),
        .WE(WE),
        .RE(RE),
        .din(din),
        .clk(clk)
    );

    initial clk = 0;
    always #5 clk = ~clk;

    initial begin
        $dumpfile("rw16x8_sync.vcd");
        $dumpvars(0, tb_rw16x8_sync);
        
        // Initial state
        WE = 0; RE = 0; address = 0; din = 0;

        #13; //sampling offset
        
        $monitor("Writing | addr = %b | din = %b", address, din);
        WE = 1; RE = 0; 
        address = 4'd0; din = 8'd10; #10;
        address = 4'd1; din = 8'd20; #10;
        address = 4'd15; din = 8'd255; #10; // Testing the last address
        
        $monitor("Read | addr = %b| dout = %b", address, dout);
        WE = 0; RE = 1;
        address = 4'd0; din = 8'd10; #10;
        address = 4'd1; din = 8'd20; #10;
        address = 4'd15; din = 8'd255; #10;

        $monitor("Both on ");
        WE = 1; RE = 1;
        address = 4'd0; din = 8'd10; #10;
        address = 4'd1; din = 8'd20; #10;
        address = 4'd15; din = 8'd255; #10;

        $monitor("Both off");
        WE = 0; RE = 0;
        address = 4'd0; din = 8'd10; #10;
        address = 4'd1; din = 8'd20; #10;
        address = 4'd15; din = 8'd255; #10;

        #150 $finish;
    end
endmodule

Memory/rw16x8_sync.vcd
$date
	Mon Apr 06 19:28:01 2026
$end
$version
	Icarus Verilog
$end
$timescale
	1ps
$end
$scope module tb_rw16x8_sync $end
$var wire 8 ! dout [7:0] $end
$var reg 1 " RE $end
$var reg 1 # WE $end
$var reg 4 $ address [3:0] $end
$var reg 1 % clk $end
$var reg 8 & din [7:0] $end
$scope module dut $end
$var wire 1 " RE $end
$var wire 1 # WE $end
$var wire 4 ' address [3:0] $end
$var wire 1 % clk $end
$var wire 8 ( din [7:0] $end
$var reg 8 ) dout [7:0] $end
$upscope $end
$upscope $end
$enddefinitions $end
$comment Show the parameter values. $end
$dumpall
$end
#0
$dumpvars
bx )
b0 (
b0 '
b0 &
0%
b0 $
0#
0"
bx !
$end
#5000
1%
#10000
0%
#13000
b1010 &
b1010 (
1#
#15000
1%
#20000
0%
#23000
b10100 &
b10100 (
b1 $
b1 '
#25000
1%
#30000
0%
#33000
b11111111 &
b11111111 (
b1111 $
b1111 '
#35000
1%
#40000
0%
#43000
b1010 &
b1010 (
b0 $
b0 '
1"
0#
#45000
b1010 !
b1010 )
1%
#50000
0%
#53000
b10100 &
b10100 (
b1 $
b1 '
#55000
b10100 !
b10100 )
1%
#60000
0%
#63000
b11111111 &
b11111111 (
b1111 $
b1111 '
#65000
b11111111 !
b11111111 )
1%
#70000
0%
#73000
b1010 &
b1010 (
b0 $
b0 '
1#
#75000
1%
#80000
0%
#83000
b10100 &
b10100 (
b1 $
b1 '
#85000
1%
#90000
0%
#93000
b11111111 &
b11111111 (
b1111 $
b1111 '
#95000
1%
#100000
0%
#103000
b1010 &
b1010 (
b0 $
b0 '
0"
0#
#105000
1%
#110000
0%
#113000
b10100 &
b10100 (
b1 $
b1 '
#115000
1%
#120000
0%
#123000
b11111111 &
b11111111 (
b1111 $
b1111 '
